mlx/unity2junit/__init__.py
mlx/unity2junit/__main__.py
mlx/unity2junit/__version__.py
mlx/unity2junit/unity2junit.py
mlx_unity2junit-0.0.8.dist-info/licenses/LICENSE
mlx_unity2junit-0.0.8.dist-info/METADATA
mlx_unity2junit-0.0.8.dist-info/WHEEL
mlx_unity2junit-0.0.8.dist-info/entry_points.txt
mlx_unity2junit-0.0.8.dist-info/top_level.txt
mlx_unity2junit-0.0.8.dist-info/RECORD
