Metadata-Version: 2.4
Name: mlx.unity2junit
Version: 0.0.8
Summary: Python script for converting Unity test framework log file to xUnit/JUnit XML
Home-page: https://github.com/melexis/unity2junit
Author-email: Anton Manzhelii <amz@melexis.com>, Crt Mori <cmo@melexis.com>
Maintainer-email: Crt Mori <cmo@melexis.com>
License-Expression: Apache-2.0
Project-URL: homepage, https://melexis.github.io/unity2junit/
Project-URL: source, https://github.com/melexis/unity2junit
Project-URL: issues, https://github.com/melexis/unity2junit/issues
Keywords: xUnit,JUnit,XML,Unity test framework,testing
Platform: any
Classifier: Development Status :: 5 - Production/Stable
Classifier: Environment :: Console
Classifier: Intended Audience :: Developers
Classifier: Operating System :: OS Independent
Classifier: Programming Language :: Python
Classifier: Programming Language :: Python :: 3
Classifier: Programming Language :: Python :: 3.8
Classifier: Programming Language :: Python :: 3.9
Classifier: Programming Language :: Python :: 3.10
Classifier: Programming Language :: Python :: 3.11
Classifier: Programming Language :: Python :: 3.12
Requires-Python: >=3.9
License-File: LICENSE
Dynamic: home-page
Dynamic: license-file
Dynamic: platform
